flinventory-0.9.3.dist-info/METADATA
flinventory-0.9.3.dist-info/WHEEL
flinventory-0.9.3.dist-info/entry_points.txt
flinventory-0.9.3.dist-info/licenses/LICENSE
flinventory/__init__.py
flinventory/__main__.py
flinventory/box.py
flinventory/constant.py
flinventory/datacleanup.py
flinventory/defaulted_data.py
flinventory/generate_labels.py
flinventory/inventory_io.py
flinventory/location.py
flinventory/sign.py
flinventory/signprinter_latex.py
flinventory/thing.py
flinventory/thingtemplate_latex/dummyImage.jpg
flinventory/thingtemplate_latex/sign.tex
flinventory/thingtemplate_latex/signlist-footer.tex
flinventory/thingtemplate_latex/signlist-header.tex
flinventory/thingtemplate_latex/signs-example.tex
flinventory-0.9.3.dist-info/RECORD
