Metadata-Version: 2.1
Name: flinventory
Version: 0.9.3
Summary: An inventory system for self-help repair shops
Author-Email: flukx <flinventory-flukx@612211124.xyz>
License: GPL3
Classifier: Development Status :: 3 - Alpha
Classifier: Intended Audience :: Customer Service
Classifier: Operating System :: OS Independent
Classifier: Programming Language :: Python :: 3.12
Classifier: Topic :: Database :: Database Engines/Servers
Classifier: Typing :: Typed
Project-URL: Homepage, https://codeberg.org/flukx/flinventory
Project-URL: Issues, https://codeberg.org/flukx/flinventory/issues
Requires-Python: >=3.12
Requires-Dist: pypandoc==1.15
Requires-Dist: python-slugify==8.0.4
Requires-Dist: treelib==1.8.0
Requires-Dist: pyyaml==6.0.2
Requires-Dist: types-pyyaml==6.0.12.20250516
Requires-Dist: pycountry==24.6.1
